flexgui.py
preferencesgui.py
scrollableframe.py
tk_flexible_preferences_gui-0.1.4.dist-info/LICENSE
tk_flexible_preferences_gui-0.1.4.dist-info/METADATA
tk_flexible_preferences_gui-0.1.4.dist-info/WHEEL
tk_flexible_preferences_gui-0.1.4.dist-info/top_level.txt
tk_flexible_preferences_gui-0.1.4.dist-info/RECORD
